shellplus/__init__.py
shellplus/colors1.py
shellplus/styles.py
shellplus-0.0.8b0.dist-info/METADATA
shellplus-0.0.8b0.dist-info/WHEEL
shellplus-0.0.8b0.dist-info/top_level.txt
shellplus-0.0.8b0.dist-info/RECORD
