Metadata-Version: 2.1
Name: shellplus
Version: 0.0.8b0
License: Unlicense
Classifier: Development Status :: 4 - Beta
Classifier: Intended Audience :: Developers
Classifier: License :: Public Domain
Classifier: Programming Language :: Python :: 3.12
Requires-Dist: rich
